Flask_Dialogflow-0.3.dist-info/DESCRIPTION.rst
Flask_Dialogflow-0.3.dist-info/METADATA
Flask_Dialogflow-0.3.dist-info/RECORD
Flask_Dialogflow-0.3.dist-info/WHEEL
Flask_Dialogflow-0.3.dist-info/metadata.json
Flask_Dialogflow-0.3.dist-info/top_level.txt
flask_dialogflow/__init__.py
flask_dialogflow/dialogflow.py
flask_dialogflow/helpers.py
flask_dialogflow/messages.py
flask_dialogflow/response.py
