Metadata-Version: 2.0
Name: Flask-Dialogflow
Version: 0.3
Summary: Simple framework for creating Dialog Flow (formerly API.AI) fulfillment webhooks
Home-page: https://github.com/gabrielrezzonico/flask-dialogflow
Author: Gabriel Rezzonico
Author-email: gabriel@byte42.com
License: MIT
Download-URL: https://github.com/gabrielrezzonico/flask-dialogflow/tarball/0.3
Platform: UNKNOWN
Classifier: Intended Audience :: Developers
Classifier: License :: OSI Approved :: MIT License
Classifier: Framework :: Flask
Classifier: Programming Language :: Python :: 2
Classifier: Programming Language :: Python :: 2.6
Classifier: Programming Language :: Python :: 2.7
Classifier: Programming Language :: Python :: 3
Classifier: Programming Language :: Python :: 3.3
Classifier: Programming Language :: Python :: 3.4
Classifier: Programming Language :: Python :: 3.5
Classifier: Programming Language :: Python :: 3.6
Classifier: Topic :: Scientific/Engineering :: Artificial Intelligence
Requires-Dist: flask
Provides-Extra: dev
Requires-Dist: sphinx; extra == 'dev'
Provides-Extra: test
Requires-Dist: pytest; extra == 'test'
Requires-Dist: pytest-cov; extra == 'test'
